pygebr/__init__.py
pygebr/flow.py
pygebr/param.py
pygebr/person.py
pygebr/program.py
pygebr/setup.py
pygebr/utils.py
pygebr/docs/catalog.html.in
pygebr/menus/others/csmodeling.json
pygebr/menus/others/dzt2rsf.json
pygebr/menus/others/menus.py
pygebr/menus/rsf/menus.py
pygebr/menus/rsf/sfacurv.json
pygebr/menus/rsf/sfadd.json
pygebr/menus/rsf/sfafac.json
pygebr/menus/rsf/sfagc.json
pygebr/menus/rsf/sfagmig.json
pygebr/menus/rsf/sfai2refl.json
pygebr/menus/rsf/sfattr.json
pygebr/menus/rsf/sfbandpass.json
pygebr/menus/rsf/sfbin.json
pygebr/menus/rsf/sfbox.json
pygebr/menus/rsf/sfcausint.json
pygebr/menus/rsf/sfclip.json
pygebr/menus/rsf/sfclip2.json
pygebr/menus/rsf/sfcontour.json
pygebr/menus/rsf/sfconv.json
pygebr/menus/rsf/sfcorral.json
pygebr/menus/rsf/sfcosft.json
pygebr/menus/rsf/sfcostaper.json
pygebr/menus/rsf/sfcpef.json
pygebr/menus/rsf/sfcut.json
pygebr/menus/rsf/sfdd.json
pygebr/menus/rsf/sfderiv.json
pygebr/menus/rsf/sfdip.json
pygebr/menus/rsf/sfdipfiltera.json
pygebr/menus/rsf/sfdipfilterv.json
pygebr/menus/rsf/sfeikonal.json
pygebr/menus/rsf/sfenvelope.json
pygebr/menus/rsf/sffft1.json
pygebr/menus/rsf/sffft3.json
pygebr/menus/rsf/sffxdecon.json
pygebr/menus/rsf/sfgraph.json
pygebr/menus/rsf/sfgrey.json
pygebr/menus/rsf/sfhalfint.json
pygebr/menus/rsf/sfheadercut.json
pygebr/menus/rsf/sfheadermath.json
pygebr/menus/rsf/sfheaderwindow.json
pygebr/menus/rsf/sfhelicon.json
pygebr/menus/rsf/sfin.json
pygebr/menus/rsf/sfintbin.json
pygebr/menus/rsf/sfinttest1.json
pygebr/menus/rsf/sfkirmod.json
pygebr/menus/rsf/sflinear.json
pygebr/menus/rsf/sflpf.json
pygebr/menus/rsf/sfltft.json
pygebr/menus/rsf/sfmask.json
pygebr/menus/rsf/sfmath.json
pygebr/menus/rsf/sfmath2.json
pygebr/menus/rsf/sfmax1.json
pygebr/menus/rsf/sfmf.json
pygebr/menus/rsf/sfmutter.json
pygebr/menus/rsf/sfnoise.json
pygebr/menus/rsf/sfpad.json
pygebr/menus/rsf/sfpatch.json
pygebr/menus/rsf/sfpen.json
pygebr/menus/rsf/sfpick.json
pygebr/menus/rsf/sfpostrtm2d.json
pygebr/menus/rsf/sfput.json
pygebr-1.3.3.dist-info/AUTHORS
pygebr-1.3.3.dist-info/COPYING
pygebr-1.3.3.dist-info/METADATA
pygebr-1.3.3.dist-info/WHEEL
pygebr-1.3.3.dist-info/top_level.txt
pygebr-1.3.3.dist-info/RECORD
