Metadata-Version: 2.1
Name: pygebr
Version: 1.3.3
Summary: PyGeBR - Processing flows made easy
Home-page: UNKNOWN
Author: Ricardo Biloti
Author-email: <biloti@unicamp.br>
License: UNKNOWN
Keywords: seismic,processing flow
Platform: UNKNOWN
Classifier: Development Status :: 5 - Production/Stable
Classifier: Intended Audience :: Developers
Classifier: Intended Audience :: Science/Research
Classifier: License :: OSI Approved :: GNU General Public License v3 (GPLv3)
Classifier: Programming Language :: Python :: 3
Classifier: Topic :: Scientific/Engineering
Requires-Python: >= 3.7.0
Requires-Dist: colorama
Requires-Dist: ipywidgets (>=8.0.0)
Requires-Dist: jsonschema (>=4.16)
